Metadata-Version: 2.1
Name: pythondata-cpu-vexriscv
Version: 1.0.1.post407
Summary: Python module containing verilog files for VexRISCV cpu.
Home-page: https://github.com/litex-hub/pythondata-cpu-vexriscv
Author: LiteX Authors
Author-email: litex@googlegroups.com
Project-URL: Bug Tracker, https://github.com/litex-hub/pythondata-cpu-vexriscv/issues
Project-URL: Source Code, https://github.com/litex-hub/pythondata-cpu-vexriscv
Classifier: Programming Language :: Python :: 3
Classifier: License :: OSI Approved :: MIT License
Classifier: Operating System :: OS Independent
Requires-Python: >=3.5
License-File: LICENSE
